{
  "envBasic": {
    "port": "8080",
    "port_com": "port for .com"
  },
  "envDbConnection": {
    "host":"localhost",
    "user":"root",
    "password":"rootPassword",
    "database":"cornerth_test",
    "port": "3306"
  },
  "envJwtSecret": {
    "userToken":"SecretKeyForUserAuth",
    "userRefresh": "SecretKeyForAuthRefresh",
    "emailVerifiedToken":"SecretKeyForEmailVerify",
    "pwforgetVerifiedToken": "SecretKeyForPwForgetVerify"
  },
  "envServiceGeneral": {
    "appDomain": "localhost:8080",
    "appProtocol": "https",
    "emailUserContact": "mailAddress@cornerth",
    "pinterestAccountLink": "https://www.pinterest.com/",
    "fbTWPageLink": "https://www.facebook.com/",
    "fbCornerthId": "0000"
  },
  "envServiceSmtp": {
    "user": "smtpAccountIfneeded",
    "password": "smtpAccountPassword"
  },
  "envAppRootPath": "/home/projectDir/",
  "envImgPath": {
    "users": "./faked/pics/",
    "marketing": "./faked/pics/",
    "file_previewApp": "preview.jpg"
  },
  "envLogPath": {
    "fromConfig": "./faked/logs/"
  },
  "envSeedPath": "./faked/dbSeeds/",
  "staticData": {
    "guidingNailsId": ["idToIntroduction","idToIntroduction"]
  }
}
